rtl/a_mean_b.v
`timescale 1ns/1ps
module a_mean_b 
(
   input  wire [7:0] in_1
  ,input  wire [7:0] in_2
  ,output wire [7:0] out_m
);
assign out_m = {1'b0, in_1[7:1]} + {1'b0, in_2[7:1]};

endmodule

rtl/TS_top.v
`timescale 1ns/1ps
module TS_top 
(
   input  wire clk // osc_16MHz
  ,input  wire RSTn
  
  ,input  wire       FLOCK
  ,input  wire       A2D_TS_DETOK
  ,input  wire [7:0] A2D_TS_DOUT
  ,input  wire       reg_ts_en_sel
  ,input  wire       reg_ts_chopper_clk_sel
  ,input  wire [3:0] reg_offset  
  
  ,output wire        D2A_TS_EN
  ,output reg        D2A_TS_START_EN
  ,output reg        D2A_TS_CLK
  ,output reg        D2A_TS_CHOPPER_CLK
  ,output reg  [3:0] ts_out
);
parameter TDH = 1;


reg  [4:0]  counter_clk;
reg  [4:0]  counter_sta;
reg  [7:0]  data_1;
reg  [7:0]  data_2;
reg  [31:0] data_buf;
reg  [3:0]  chop_phase;
wire [31:0] data_sum_tmp;
wire [7:0]  in_1, in_2, out_m;

//------------------clk_320k
always@(posedge clk or negedge RSTn) begin
  if (!RSTn) 
    counter_clk <= #(TDH) 5'd0;
  else if (counter_clk == 5'd24)
    counter_clk <= #(TDH) 5'd0;
  else
    counter_clk <= #(TDH) counter_clk + 5'd1;
end
/*
reg clk_320k;
always@(posedge clk or negedge RSTn) begin
  if (!RSTn) 
    clk_320k <= #(TDH) 1'd0;
  else if (counter_clk == 5'd24)
    clk_320k <= #(TDH) ~clk_320k;
  else 
    clk_320k <= #(TDH) clk_320k;
end
*/
//----------------------start en
always@(posedge clk or negedge RSTn) begin
  if (!RSTn) 
    counter_sta <= #(TDH) 5'd0;
  else if (counter_sta == 5'd20)
    counter_sta <= #(TDH) 5'd0;
  else if (counter_clk == 5'd23)
    counter_sta <= #(TDH) counter_sta + 5'd1;
  else 
    counter_sta <= #(TDH) counter_sta;
end

always@(posedge clk or negedge RSTn) begin
  if (!RSTn) 
    D2A_TS_START_EN <= #(TDH) 1'd0;
  else if (counter_sta == 5'd1)
    D2A_TS_START_EN <= #(TDH) 1'd1;
  else if (counter_sta == 5'd2)
    D2A_TS_START_EN <= #(TDH) 1'd0;
  else
    D2A_TS_START_EN <= #(TDH) D2A_TS_START_EN;
end
//-------------------ts en
assign D2A_TS_EN = reg_ts_en_sel ? FLOCK : 1'b1;
//---------------------chopper
always@(posedge clk or negedge RSTn) begin
  if (!RSTn) 
    D2A_TS_CHOPPER_CLK <= #(TDH) 1'd0;
  else if( counter_sta == 5'd1 && counter_clk == 5'd24 )
    D2A_TS_CHOPPER_CLK <= #(TDH) ~D2A_TS_CHOPPER_CLK;
  else
    D2A_TS_CHOPPER_CLK <= #(TDH) D2A_TS_CHOPPER_CLK;
end
//---------ts clk
always@(posedge clk or negedge RSTn) begin
  if (!RSTn) 
    D2A_TS_CLK <= #(TDH) 1'd0;
  else if (counter_sta == 5'd1 || counter_sta == 5'd2)
    D2A_TS_CLK <= #(TDH) 1'd0;
  else if (counter_clk == 5'd24)
    D2A_TS_CLK <= #(TDH) ~D2A_TS_CLK;
  else 
    D2A_TS_CLK <= #(TDH) D2A_TS_CLK;
end
//--------chop phase
always@(posedge A2D_TS_DETOK or negedge RSTn) begin
  if (!RSTn) 
    chop_phase <= #(TDH) 4'd0;
  else 
    chop_phase <= #(TDH) chop_phase + 4'd1;
end

//-----------data calculate

always@(posedge A2D_TS_DETOK or negedge RSTn) begin
  if (!RSTn) 
    data_1 <= #(TDH) 8'b01110000;
  else if (D2A_TS_CHOPPER_CLK == 1'd1)
    data_1 <= #(TDH) A2D_TS_DOUT;
  else 
    data_1 <= #(TDH) data_1;
end
always@(posedge A2D_TS_DETOK or negedge RSTn) begin
  if (!RSTn) 
    data_2 <= #(TDH) 8'b01110000;
  else if (D2A_TS_CHOPPER_CLK == 1'd0)
    data_2 <= #(TDH) A2D_TS_DOUT;
  else 
    data_2 <= #(TDH) data_2;
end

wire rstn_data_tmp = RSTn & ~(D2A_TS_START_EN & (chop_phase == 4'd0));
wire clk_data_tmp_gate = D2A_TS_CLK & ( A2D_TS_DETOK == 1'b1);
always@(posedge clk_data_tmp_gate or negedge rstn_data_tmp) begin
  if (!rstn_data_tmp) 
    data_buf <= #(TDH) 32'd0;
//  else if (A2D_TS_DETOK == 1'b1)
//    data_buf <= #(TDH) data_sum_tmp;
  else
    data_buf <= #(TDH) data_sum_tmp;

end

a_mean_b a_mean_b(.in_1(in_1),.in_2(in_2),.out_m(out_m));
assign data_sum_tmp = (chop_phase == 4'd5 & A2D_TS_DETOK == 1'b0) ? {data_buf[31:8], out_m } :
                      (chop_phase == 4'd9 & A2D_TS_DETOK == 1'b0) ? {data_buf[31:16], data_buf[23:16], out_m } :
					  (chop_phase == 4'd11 & A2D_TS_DETOK == 1'b0) ? {data_buf[31:8], out_m } :					  
					  (chop_phase == 4'd13 & A2D_TS_DETOK == 1'b0) ? {data_buf[31:16], data_buf[15:8], out_m } :
				      (chop_phase != 4'd4 & D2A_TS_CHOPPER_CLK == 1'b1 ) ? {data_buf[23:0], out_m } ://shift
					  data_buf;
assign in_1 = (D2A_TS_CHOPPER_CLK == 1'b1) ? data_1 : 
              (chop_phase == 4'd5 & A2D_TS_DETOK == 1'b0) ? data_buf[7:0] :
			  (chop_phase == 4'd9 & A2D_TS_DETOK == 1'b0) ? data_buf[7:0] :
			  (chop_phase == 4'd11 & A2D_TS_DETOK == 1'b0) ? data_buf[7:0] :			  
			  (chop_phase == 4'd13 & A2D_TS_DETOK == 1'b0) ? data_buf[7:0] :
			  data_1;
assign in_2 = (D2A_TS_CHOPPER_CLK == 1'b1) ? data_1 : 
              (chop_phase == 4'd5 & A2D_TS_DETOK == 1'b0) ? data_buf[15:8] : 
			  (chop_phase == 4'd9 & A2D_TS_DETOK == 1'b0) ? data_buf[15:8] : 
			  (chop_phase == 4'd11 & A2D_TS_DETOK == 1'b0) ? data_buf[15:8] :
			  (chop_phase == 4'd13 & A2D_TS_DETOK == 1'b0) ? data_buf[15:8] :
			  data_2;



endmodule

rtl/testbench.v
`timescale 1ns/1ps
module test_bench ();

//**************************** wire & reg**********************//
  reg clk; // osc_16MHz
  reg RSTn;
  reg FLOCK;
 

//**************************** module **********************//
initial $display("===module : TS_top");
TS_top TS_top(
   .clk(clk) // osc_16MHz
  ,.RSTn(RSTn)
  
  ,.FLOCK(FLOCK)
  ,.A2D_TS_DETOK(1'd0)
  ,.A2D_TS_DOUT(8'd0)
  ,.reg_ts_en_sel(1'd0)
  ,.reg_ts_chopper_clk_sel(1'd0)
  ,.reg_offset(4'd0)
  
  ,.D2A_TS_EN()
  ,.D2A_TS_START_EN()
  ,.D2A_TS_CLK()
  ,.D2A_TS_CHOPPER_CLK()
  ,.ts_out()
);
//**************************** clock **********************//
`define CYCLE 31.25
initial begin
	force clk = 1'b0;
    @(negedge TS_top.RSTn);
    @(posedge TS_top.RSTn);
	$display("===starting generating clk");
	forever #(`CYCLE) force TS_top.clk = ~TS_top.clk;
end

//*******************************reset******************//
initial begin
	$display("===starting initial reset");
	force TS_top.RSTn = 1'b1;
	#1_000;
	force TS_top.RSTn = 1'b0;
	#1_000;
	force TS_top.RSTn = 1'b1;
end

//**************************** initial and wavegen **********************//
initial 
begin
	$display("===starting dump waveform");
	$dumpfile("out.vcd");
	$dumpvars(0,TS_top);
end

//**************************** main **********************//

initial
begin
    @(negedge TS_top.RSTn);
    @(posedge TS_top.RSTn);
	//waiting reset


	$display("===all done");
	#1000000 $finish;
end

always begin
  @(posedge TS_top.D2A_TS_START_EN);
  force TS_top.A2D_TS_DETOK = 1'd0;
  #26562.5ns;
  force TS_top.A2D_TS_DETOK = 1'd1;
end

always begin
  @(posedge TS_top.D2A_TS_START_EN);
  force TS_top.A2D_TS_DOUT = TS_top.A2D_TS_DOUT + 8'd1;
end

//*******************************end**************************//
endmodule

out.vcd
$date
	Fri Jun 07 19:54:34 2019
$end
$version
	Icarus Verilog
$end
$timescale
	1ps
$end
$scope module test_bench $end
$scope module TS_top $end
$var wire 1 ! A2D_TS_DETOK $end
$var wire 8 " A2D_TS_DOUT [7:0] $end
$var wire 1 # D2A_TS_EN $end
$var wire 1 $ FLOCK $end
$var wire 1 % RSTn $end
$var wire 1 & clk $end
$var wire 1 ' clk_data_tmp_gate $end
$var wire 4 ( reg_offset [3:0] $end
$var wire 1 ) reg_ts_chopper_clk_sel $end
$var wire 1 * reg_ts_en_sel $end
$var wire 1 + rstn_data_tmp $end
$var wire 8 , out_m [7:0] $end
$var wire 8 - in_2 [7:0] $end
$var wire 8 . in_1 [7:0] $end
$var wire 32 / data_sum_tmp [31:0] $end
$var reg 1 0 D2A_TS_CHOPPER_CLK $end
$var reg 1 1 D2A_TS_CLK $end
$var reg 1 2 D2A_TS_START_EN $end
$var reg 4 3 chop_phase [3:0] $end
$var reg 5 4 counter_clk [4:0] $end
$var reg 5 5 counter_sta [4:0] $end
$var reg 8 6 data_1 [7:0] $end
$var reg 8 7 data_2 [7:0] $end
$var reg 32 8 data_buf [31:0] $end
$var reg 4 9 ts_out [3:0] $end
$scope module a_mean_b $end
$var wire 8 : in_1 [7:0] $end
$var wire 8 ; in_2 [7:0] $end
$var wire 8 < out_m [7:0] $end
$upscope $end
$upscope $end
$upscope $end
$enddefinitions $end
#0
$dumpvars
bx <
bx ;
bx :
bx 9
bx 8
bx 7
bx 6
bx 5
bx 4
bx 3
x2
x1
x0
bx /
bx .
bx -
bx ,
x+
0*
0)
b0 (
0'
0&
1%
x$
1#
b0 "
0!
$end
#1000000
0+
0%
#1001000
b1110000 ,
b1110000 <
b1110000 .
b1110000 :
b1110000 -
b1110000 ;
b0 /
b0 8
b0 3
b1110000 6
b1110000 7
b0 4
b0 5
02
00
01
#2000000
1+
1%
#2031250
1&
#2032250
b1 4
#2062500
0&
#2093750
1&
#2094750
b10 4
#2125000
0&
#2156250
1&
#2157250
b11 4
#2187500
0&
#2218750
1&
#2219750
b100 4
#2250000
0&
#2281250
1&
#2282250
b101 4
#2312500
0&
#2343750
1&
#2344750
b110 4
#2375000
0&
#2406250
1&
#2407250
b111 4
#2437500
0&
#2468750
1&
#2469750
b1000 4
#2500000
0&
#2531250
1&
#2532250
b1001 4
#2562500
0&
#2593750
1&
#2594750
b1010 4
#2625000
0&
#2656250
1&
#2657250
b1011 4
#2687500
0&
#2718750
1&
#2719750
b1100 4
#2750000
0&
#2781250
1&
#2782250
b1101 4
#2812500
0&
#2843750
1&
#2844750
b1110 4
#2875000
0&
#2906250
1&
#2907250
b1111 4
#2937500
0&
#2968750
1&
#2969750
b10000 4
#3000000
0&
#3031250
1&
#3032250
b10001 4
#3062500
0&
#3093750
1&
#3094750
b10010 4
#3125000
0&
#3156250
1&
#3157250
b10011 4
#3187500
0&
#3218750
1&
#3219750
b10100 4
#3250000
0&
#3281250
1&
#3282250
b10101 4
#3312500
0&
#3343750
1&
#3344750
b10110 4
#3375000
0&
#3406250
1&
#3407250
b10111 4
#3437500
0&
#3468750
1&
#3469750
b11000 4
b1 5
#3500000
0&
#3531250
1&
#3532250
b1110000 /
0+
0!
b1 "
10
12
b0 4
#3562500
0&
#3593750
1&
#3594750
b1 4
#3625000
0&
#3656250
1&
#3657250
b10 4
#3687500
0&
#3718750
1&
#3719750
b11 4
#3750000
0&
#3781250
1&
#3782250
b100 4
#3812500
0&
#3843750
1&
#3844750
b101 4
#3875000
0&
#3906250
1&
#3907250
b110 4
#3937500
0&
#3968750
1&
#3969750
b111 4
#4000000
0&
#4031250
1&
#4032250
b1000 4
#4062500
0&
#4093750
1&
#4094750
b1001 4
#4125000
0&
#4156250
1&
#4157250
b1010 4
#4187500
0&
#4218750
1&
#4219750
b1011 4
#4250000
0&
#4281250
1&
#4282250
b1100 4
#4312500
0&
#4343750
1&
#4344750
b1101 4
#4375000
0&
#4406250
1&
#4407250
b1110 4
#4437500
0&
#4468750
1&
#4469750
b1111 4
#4500000
0&
#4531250
1&
#4532250
b10000 4
#4562500
0&
#4593750
1&
#4594750
b10001 4
#4625000
0&
#4656250
1&
#4657250
b10010 4
#4687500
0&
#4718750
1&
#4719750
b10011 4
#4750000
0&
#4781250
1&
#4782250
b10100 4
#4812500
0&
#4843750
1&
#4844750
b10101 4
#4875000
0&
#4906250
1&
#4907250
b10110 4
#4937500
0&
#4968750
1&
#4969750
b10111 4
#5000000
0&
#5031250
1&
#5032250
b10 5
b11000 4
#5062500
0&
#5093750
1&
#5094750
1+
b0 4
02
#5125000
0&
#5156250
1&
#5157250
b1 4
#5187500
0&
#5218750
1&
#5219750
b10 4
#5250000
0&
#5281250
1&
#5282250
b11 4
#5312500
0&
#5343750
1&
#5344750
b100 4
#5375000
0&
#5406250
1&
#5407250
b101 4
#5437500
0&
#5468750
1&
#5469750
b110 4
#5500000
0&
#5531250
1&
#5532250
b111 4
#5562500
0&
#5593750
1&
#5594750
b1000 4
#5625000
0&
#5656250
1&
#5657250
b1001 4
#5687500
0&
#5718750
1&
#5719750
b1010 4
#5750000
0&
#5781250
1&
#5782250
b1011 4
#5812500
0&
#5843750
1&
#5844750
b1100 4
#5875000
0&
#5906250
1&
#5907250
b1101 4
#5937500
0&
#5968750
1&
#5969750
b1110 4
#6000000
0&
#6031250
1&
#6032250
b1111 4
#6062500
0&
#6093750
1&
#6094750
b10000 4
#6125000
0&
#6156250
1&
#6157250
b10001 4
#6187500
0&
#6218750
1&
#6219750
b10010 4
#6250000
0&
#6281250
1&
#6282250
b10011 4
#6312500
0&
#6343750
1&
#6344750
b10100 4
#6375000
0&
#6406250
1&
#6407250
b10101 4
#6437500
0&
#6468750
1&
#6469750
b10110 4
#6500000
0&
#6531250
1&
#6532250
b10111 4
#6562500
0&
#6593750
1&
#6594750
b11000 4
b11 5
#6625000
0&
#6656250
1&
#6657250
11
b0 4
#6687500
0&
#6718750
1&
#6719750
b1 4
#6750000
0&
#6781250
1&
#6782250
b10 4
#6812500
0&
#6843750
1&
#6844750
b11 4
#6875000
0&
#6906250
1&
#6907250
b100 4
#6937500
0&
#6968750
1&
#6969750
b101 4
#7000000
0&
#7031250
1&
#7032250
b110 4
#7062500
0&
#7093750
1&
#7094750
b111 4
#7125000
0&
#7156250
1&
#7157250
b1000 4
#7187500
0&
#7218750
1&
#7219750
b1001 4
#7250000
0&
#7281250
1&
#7282250
b1010 4
#7312500
0&
#7343750
1&
#7344750
b1011 4
#7375000
0&
#7406250
1&
#7407250
b1100 4
#7437500
0&
#7468750
1&
#7469750
b1101 4
#7500000
0&
#7531250
1&
#7532250
b1110 4
#7562500
0&
#7593750
1&
#7594750
b1111 4
#7625000
0&
#7656250
1&
#7657250
b10000 4
#7687500
0&
#7718750
1&
#7719750
b10001 4
#7750000
0&
#7781250
1&
#7782250
b10010 4
#7812500
0&
#7843750
1&
#7844750
b10011 4
#7875000
0&
#7906250
1&
#7907250
b10100 4
#7937500
0&
#7968750
1&
#7969750
b10101 4
#8000000
0&
#8031250
1&
#8032250
b10110 4
#8062500
0&
#8093750
1&
#8094750
b10111 4
#8125000
0&
#8156250
1&
#8157250
b100 5
b11000 4
#8187500
0&
#8218750
1&
#8219750
b0 4
01
#8250000
0&
#8281250
1&
#8282250
b1 4
#8312500
0&
#8343750
1&
#8344750
b10 4
#8375000
0&
#8406250
1&
#8407250
b11 4
#8437500
0&
#8468750
1&
#8469750
b100 4
#8500000
0&
#8531250
1&
#8532250
b101 4
#8562500
0&
#8593750
1&
#8594750
b110 4
#8625000
0&
#8656250
1&
#8657250
b111 4
#8687500
0&
#8718750
1&
#8719750
b1000 4
#8750000
0&
#8781250
1&
#8782250
b1001 4
#8812500
0&
#8843750
1&
#8844750
b1010 4
#8875000
0&
#8906250
1&
#8907250
b1011 4
#8937500
0&
#8968750
1&
#8969750
b1100 4
#9000000
0&
#9031250
1&
#9032250
b1101 4
#9062500
0&
#9093750
1&
#9094750
b1110 4
#9125000
0&
#9156250
1&
#9157250
b1111 4
#9187500
0&
#9218750
1&
#9219750
b10000 4
#9250000
0&
#9281250
1&
#9282250
b10001 4
#9312500
0&
#9343750
1&
#9344750
b10010 4
#9375000
0&
#9406250
1&
#9407250
b10011 4
#9437500
0&
#9468750
1&
#9469750
b10100 4
#9500000
0&
#9531250
1&
#9532250
b10101 4
#9562500
0&
#9593750
1&
#9594750
b10110 4
#9625000
0&
#9656250
1&
#9657250
b10111 4
#9687500
0&
#9718750
1&
#9719750
b11000 4
b101 5
#9750000
0&
#9781250
1&
#9782250
11
b0 4
#9812500
0&
#9843750
1&
#9844750
b1 4
#9875000
0&
#9906250
1&
#9907250
b10 4
#9937500
0&
#9968750
1&
#9969750
b11 4
#10000000
0&
#10031250
1&
#10032250
b100 4
#10062500
0&
#10093750
1&
#10094750
b101 4
#10125000
0&
#10156250
1&
#10157250
b110 4
#10187500
0&
#10218750
1&
#10219750
b111 4
#10250000
0&
#10281250
1&
#10282250
b1000 4
#10312500
0&
#10343750
1&
#10344750
b1001 4
#10375000
0&
#10406250
1&
#10407250
b1010 4
#10437500
0&
#10468750
1&
#10469750
b1011 4
#10500000
0&
#10531250
1&
#10532250
b1100 4
#10562500
0&
#10593750
1&
#10594750
b1101 4
#10625000
0&
#10656250
1&
#10657250
b1110 4
#10687500
0&
#10718750
1&
#10719750
b1111 4
#10750000
0&
#10781250
1&
#10782250
b10000 4
#10812500
0&
#10843750
1&
#10844750
b10001 4
#10875000
0&
#10906250
1&
#10907250
b10010 4
#10937500
0&
#10968750
1&
#10969750
b10011 4
#11000000
0&
#11031250
1&
#11032250
b10100 4
#11062500
0&
#11093750
1&
#11094750
b10101 4
#11125000
0&
#11156250
1&
#11157250
b10110 4
#11187500
0&
#11218750
1&
#11219750
b10111 4
#11250000
0&
#11281250
1&
#11282250
b110 5
b11000 4
#11312500
0&
#11343750
1&
#11344750
b0 4
01
#11375000
0&
#11406250
1&
#11407250
b1 4
#11437500
0&
#11468750
1&
#11469750
b10 4
#11500000
0&
#11531250
1&
#11532250
b11 4
#11562500
0&
#11593750
1&
#11594750
b100 4
#11625000
0&
#11656250
1&
#11657250
b101 4
#11687500
0&
#11718750
1&
#11719750
b110 4
#11750000
0&
#11781250
1&
#11782250
b111 4
#11812500
0&
#11843750
1&
#11844750
b1000 4
#11875000
0&
#11906250
1&
#11907250
b1001 4
#11937500
0&
#11968750
1&
#11969750
b1010 4
#12000000
0&
#12031250
1&
#12032250
b1011 4
#12062500
0&
#12093750
1&
#12094750
b1100 4
#12125000
0&
#12156250
1&
#12157250
b1101 4
#12187500
0&
#12218750
1&
#12219750
b1110 4
#12250000
0&
#12281250
1&
#12282250
b1111 4
#12312500
0&
#12343750
1&
#12344750
b10000 4
#12375000
0&
#12406250
1&
#12407250
b10001 4
#12437500
0&
#12468750
1&
#12469750
b10010 4
#12500000
0&
#12531250
1&
#12532250
b10011 4
#12562500
0&
#12593750
1&
#12594750
b10100 4
#12625000
0&
#12656250
1&
#12657250
b10101 4
#12687500
0&
#12718750
1&
#12719750
b10110 4
#12750000
0&
#12781250
1&
#12782250
b10111 4
#12812500
0&
#12843750
1&
#12844750
b11000 4
b111 5
#12875000
0&
#12906250
1&
#12907250
11
b0 4
#12937500
0&
#12968750
1&
#12969750
b1 4
#13000000
0&
#13031250
1&
#13032250
b10 4
#13062500
0&
#13093750
1&
#13094750
b11 4
#13125000
0&
#13156250
1&
#13157250
b100 4
#13187500
0&
#13218750
1&
#13219750
b101 4
#13250000
0&
#13281250
1&
#13282250
b110 4
#13312500
0&
#13343750
1&
#13344750
b111 4
#13375000
0&
#13406250
1&
#13407250
b1000 4
#13437500
0&
#13468750
1&
#13469750
b1001 4
#13500000
0&
#13531250
1&
#13532250
b1010 4
#13562500
0&
#13593750
1&
#13594750
b1011 4
#13625000
0&
#13656250
1&
#13657250
b1100 4
#13687500
0&
#13718750
1&
#13719750
b1101 4
#13750000
0&
#13781250
1&
#13782250
b1110 4
#13812500
0&
#13843750
1&
#13844750
b1111 4
#13875000
0&
#13906250
1&
#13907250
b10000 4
#13937500
0&
#13968750
1&
#13969750
b10001 4
#14000000
0&
#14031250
1&
#14032250
b10010 4
#14062500
0&
#14093750
1&
#14094750
b10011 4
#14125000
0&
#14156250
1&
#14157250
b10100 4
#14187500
0&
#14218750
1&
#14219750
b10101 4
#14250000
0&
#14281250
1&
#14282250
b10110 4
#14312500
0&
#14343750
1&
#14344750
b10111 4
#14375000
0&
#14406250
1&
#14407250
b1000 5
b11000 4
#14437500
0&
#14468750
1&
#14469750
b0 4
01
#14500000
0&
#14531250
1&
#14532250
b1 4
#14562500
0&
#14593750
1&
#14594750
b10 4
#14625000
0&
#14656250
1&
#14657250
b11 4
#14687500
0&
#14718750
1&
#14719750
b100 4
#14750000
0&
#14781250
1&
#14782250
b101 4
#14812500
0&
#14843750
1&
#14844750
b110 4
#14875000
0&
#14906250
1&
#14907250
b111 4
#14937500
0&
#14968750
1&
#14969750
b1000 4
#15000000
0&
#15031250
1&
#15032250
b1001 4
#15062500
0&
#15093750
1&
#15094750
b1010 4
#15125000
0&
#15156250
1&
#15157250
b1011 4
#15187500
0&
#15218750
1&
#15219750
b1100 4
#15250000
0&
#15281250
1&
#15282250
b1101 4
#15312500
0&
#15343750
1&
#15344750
b1110 4
#15375000
0&
#15406250
1&
#15407250
b1111 4
#15437500
0&
#15468750
1&
#15469750
b10000 4
#15500000
0&
#15531250
1&
#15532250
b10001 4
#15562500
0&
#15593750
1&
#15594750
b10010 4
#15625000
0&
#15656250
1&
#15657250
b10011 4
#15687500
0&
#15718750
1&
#15719750
b10100 4
#15750000
0&
#15781250
1&
#15782250
b10101 4
#15812500
0&
#15843750
1&
#15844750
b10110 4
#15875000
0&
#15906250
1&
#15907250
b10111 4
#15937500
0&
#15968750
1&
#15969750
b11000 4
b1001 5
#16000000
0&
#16031250
1&
#16032250
11
b0 4
#16062500
0&
#16093750
1&
#16094750
b1 4
#16125000
0&
#16156250
1&
#16157250
b10 4
#16187500
0&
#16218750
1&
#16219750
b11 4
#16250000
0&
#16281250
1&
#16282250
b100 4
#16312500
0&
#16343750
1&
#16344750
b101 4
#16375000
0&
#16406250
1&
#16407250
b110 4
#16437500
0&
#16468750
1&
#16469750
b111 4
#16500000
0&
#16531250
1&
#16532250
b1000 4
#16562500
0&
#16593750
1&
#16594750
b1001 4
#16625000
0&
#16656250
1&
#16657250
b1010 4
#16687500
0&
#16718750
1&
#16719750
b1011 4
#16750000
0&
#16781250
1&
#16782250
b1100 4
#16812500
0&
#16843750
1&
#16844750
b1101 4
#16875000
0&
#16906250
1&
#16907250
b1110 4
#16937500
0&
#16968750
1&
#16969750
b1111 4
#17000000
0&
#17031250
1&
#17032250
b10000 4
#17062500
0&
#17093750
1&
#17094750
b10001 4
#17125000
0&
#17156250
1&
#17157250
b10010 4
#17187500
0&
#17218750
1&
#17219750
b10011 4
#17250000
0&
#17281250
1&
#17282250
b10100 4
#17312500
0&
#17343750
1&
#17344750
b10101 4
#17375000
0&
#17406250
1&
#17407250
b10110 4
#17437500
0&
#17468750
1&
#17469750
b10111 4
#17500000
0&
#17531250
1&
#17532250
b1010 5
b11000 4
#17562500
0&
#17593750
1&
#17594750
b0 4
01
#17625000
0&
#17656250
1&
#17657250
b1 4
#17687500
0&
#17718750
1&
#17719750
b10 4
#17750000
0&
#17781250
1&
#17782250
b11 4
#17812500
0&
#17843750
1&
#17844750
b100 4
#17875000
0&
#17906250
1&
#17907250
b101 4
#17937500
0&
#17968750
1&
#17969750
b110 4
#18000000
0&
#18031250
1&
#18032250
b111 4
#18062500
0&
#18093750
1&
#18094750
b1000 4
#18125000
0&
#18156250
1&
#18157250
b1001 4
#18187500
0&
#18218750
1&
#18219750
b1010 4
#18250000
0&
#18281250
1&
#18282250
b1011 4
#18312500
0&
#18343750
1&
#18344750
b1100 4
#18375000
0&
#18406250
1&
#18407250
b1101 4
#18437500
0&
#18468750
1&
#18469750
b1110 4
#18500000
0&
#18531250
1&
#18532250
b1111 4
#18562500
0&
#18593750
1&
#18594750
b10000 4
#18625000
0&
#18656250
1&
#18657250
b10001 4
#18687500
0&
#18718750
1&
#18719750
b10010 4
#18750000
0&
#18781250
1&
#18782250
b10011 4
#18812500
0&
#18843750
1&
#18844750
b10100 4
#18875000
0&
#18906250
1&
#18907250
b10101 4
#18937500
0&
#18968750
1&
#18969750
b10110 4
#19000000
0&
#19031250
1&
#19032250
b10111 4
#19062500
0&
#19093750
1&
#19094750
b11000 4
b1011 5
#19125000
0&
#19156250
1&
#19157250
11
b0 4
#19187500
0&
#19218750
1&
#19219750
b1 4
#19250000
0&
#19281250
1&
#19282250
b10 4
#19312500
0&
#19343750
1&
#19344750
b11 4
#19375000
0&
#19406250
1&
#19407250
b100 4
#19437500
0&
#19468750
1&
#19469750
b101 4
#19500000
0&
#19531250
1&
#19532250
b110 4
#19562500
0&
#19593750
1&
#19594750
b111 4
#19625000
0&
#19656250
1&
#19657250
b1000 4
#19687500
0&
#19718750
1&
#19719750
b1001 4
#19750000
0&
#19781250
1&
#19782250
b1010 4
#19812500
0&
#19843750
1&
#19844750
b1011 4
#19875000
0&
#19906250
1&
#19907250
b1100 4
#19937500
0&
#19968750
1&
#19969750
b1101 4
#20000000
0&
#20031250
1&
#20032250
b1110 4
#20062500
0&
#20093750
1&
#20094750
b1111 4
#20125000
0&
#20156250
1&
#20157250
b10000 4
#20187500
0&
#20218750
1&
#20219750
b10001 4
#20250000
0&
#20281250
1&
#20282250
b10010 4
#20312500
0&
#20343750
1&
#20344750
b10011 4
#20375000
0&
#20406250
1&
#20407250
b10100 4
#20437500
0&
#20468750
1&
#20469750
b10101 4
#20500000
0&
#20531250
1&
#20532250
b10110 4
#20562500
0&
#20593750
1&
#20594750
b10111 4
#20625000
0&
#20656250
1&
#20657250
b1100 5
b11000 4
#20687500
0&
#20718750
1&
#20719750
b0 4
01
#20750000
0&
#20781250
1&
#20782250
b1 4
#20812500
0&
#20843750
1&
#20844750
b10 4
#20875000
0&
#20906250
1&
#20907250
b11 4
#20937500
0&
#20968750
1&
#20969750
b100 4
#21000000
0&
#21031250
1&
#21032250
b101 4
#21062500
0&
#21093750
1&
#21094750
b110 4
#21125000
0&
#21156250
1&
#21157250
b111 4
#21187500
0&
#21218750
1&
#21219750
b1000 4
#21250000
0&
#21281250
1&
#21282250
b1001 4
#21312500
0&
#21343750
1&
#21344750
b1010 4
#21375000
0&
#21406250
1&
#21407250
b1011 4
#21437500
0&
#21468750
1&
#21469750
b1100 4
#21500000
0&
#21531250
1&
#21532250
b1101 4
#21562500
0&
#21593750
1&
#21594750
b1110 4
#21625000
0&
#21656250
1&
#21657250
b1111 4
#21687500
0&
#21718750
1&
#21719750
b10000 4
#21750000
0&
#21781250
1&
#21782250
b10001 4
#21812500
0&
#21843750
1&
#21844750
b10010 4
#21875000
0&
#21906250
1&
#21907250
b10011 4
#21937500
0&
#21968750
1&
#21969750
b10100 4
#22000000
0&
#22031250
1&
#22032250
b10101 4
#22062500
0&
#22093750
1&
#22094750
b10110 4
#22125000
0&
#22156250
1&
#22157250
b10111 4
#22187500
0&
#22218750
1&
#22219750
b11000 4
b1101 5
#22250000
0&
#22281250
1&
#22282250
11
b0 4
#22312500
0&
#22343750
1&
#22344750
b1 4
#22375000
0&
#22406250
1&
#22407250
b10 4
#22437500
0&
#22468750
1&
#22469750
b11 4
#22500000
0&
#22531250
1&
#22532250
b100 4
#22562500
0&
#22593750
1&
#22594750
b101 4
#22625000
0&
#22656250
1&
#22657250
b110 4
#22687500
0&
#22718750
1&
#22719750
b111 4
#22750000
0&
#22781250
1&
#22782250
b1000 4
#22812500
0&
#22843750
1&
#22844750
b1001 4
#22875000
0&
#22906250
1&
#22907250
b1010 4
#22937500
0&
#22968750
1&
#22969750
b1011 4
#23000000
0&
#23031250
1&
#23032250
b1100 4
#23062500
0&
#23093750
1&
#23094750
b1101 4
#23125000
0&
#23156250
1&
#23157250
b1110 4
#23187500
0&
#23218750
1&
#23219750
b1111 4
#23250000
0&
#23281250
1&
#23282250
b10000 4
#23312500
0&
#23343750
1&
#23344750
b10001 4
#23375000
0&
#23406250
1&
#23407250
b10010 4
#23437500
0&
#23468750
1&
#23469750
b10011 4
#23500000
0&
#23531250
1&
#23532250
b10100 4
#23562500
0&
#23593750
1&
#23594750
b10101 4
#23625000
0&
#23656250
1&
#23657250
b10110 4
#23687500
0&
#23718750
1&
#23719750
b10111 4
#23750000
0&
#23781250
1&
#23782250
b1110 5
b11000 4
#23812500
0&
#23843750
1&
#23844750
b0 4
01
#23875000
0&
#23906250
1&
#23907250
b1 4
#23937500
0&
#23968750
1&
#23969750
b10 4
#24000000
0&
#24031250
1&
#24032250
b11 4
#24062500
0&
#24093750
1&
#24094750
b100 4
#24125000
0&
#24156250
1&
#24157250
b101 4
#24187500
0&
#24218750
1&
#24219750
b110 4
#24250000
0&
#24281250
1&
#24282250
b111 4
#24312500
0&
#24343750
1&
#24344750
b1000 4
#24375000
0&
#24406250
1&
#24407250
b1001 4
#24437500
0&
#24468750
1&
#24469750
b1010 4
#24500000
0&
#24531250
1&
#24532250
b1011 4
#24562500
0&
#24593750
1&
#24594750
b1100 4
#24625000
0&
#24656250
1&
#24657250
b1101 4
#24687500
0&
#24718750
1&
#24719750
b1110 4
#24750000
0&
#24781250
1&
#24782250
b1111 4
#24812500
0&
#24843750
1&
#24844750
b10000 4
#24875000
0&
#24906250
1&
#24907250
b10001 4
#24937500
0&
#24968750
1&
#24969750
b10010 4
#25000000
0&
#25031250
1&
#25032250
b10011 4
#25062500
0&
#25093750
1&
#25094750
b10100 4
#25125000
0&
#25156250
1&
#25157250
b10101 4
#25187500
0&
#25218750
1&
